TcArch.py
TcArch-0.0.5.dist-info/LICENSE
TcArch-0.0.5.dist-info/METADATA
TcArch-0.0.5.dist-info/WHEEL
TcArch-0.0.5.dist-info/top_level.txt
TcArch-0.0.5.dist-info/RECORD
